pydb/__init__.py
pydb/db.py
pydb/utils.py
python_db-0.0.5.data/scripts/db
python_db-0.0.5.dist-info/METADATA
python_db-0.0.5.dist-info/WHEEL
python_db-0.0.5.dist-info/top_level.txt
python_db-0.0.5.dist-info/RECORD
